{
  "trackId": "1ffdbb7c-9a2d-4412-854a-b48aa52a18ad",
  "fecha": "2026-05-26T15:12:03.122Z",
  "estado": "RECHAZADO",
  "environment": "certecf",
  "codigo": "2",
  "descripcion": null,
  "mensaje": null,
  "error": null,
  "rnc": "40211932609",
  "encf": "E310000000009",
  "secuenciaUtilizada": false,
  "fechaRecepcion": "5/26/2026 11:11:03 AM",
  "mensajes": [
    {
      "valor": "La propiedad NombreComercial no es válida debido a que el valor enviado () no coincide con el valor (DOCUMENTOS ELECTRONICOS DE 02) del conjunto de datos entregados.",
      "codigo": 0
    }
  ],
  "httpStatus": 200,
  "raw": "{\"trackId\":\"1ffdbb7c-9a2d-4412-854a-b48aa52a18ad\",\"codigo\":\"2\",\"estado\":\"Rechazado\",\"rnc\":\"40211932609\",\"encf\":\"E310000000009\",\"secuenciaUtilizada\":false,\"fechaRecepcion\":\"5/26/2026 11:11:03 AM\",\"mensajes\":[{\"valor\":\"La propiedad NombreComercial no es válida debido a que el valor enviado () no coincide con el valor (DOCUMENTOS ELECTRONICOS DE 02) del conjunto de datos entregados.\",\"codigo\":0}]}",
  "statusPath": "storage/ecf/tracks/estado-1ffdbb7c-9a2d-4412-854a-b48aa52a18ad.json"
}
