{
  "trackId": "9f971e0f-9e3b-46cd-a767-2478893eaa9b",
  "fecha": "2026-05-28T04:41:37.155Z",
  "estado": "ACEPTADO",
  "environment": "certecf",
  "codigo": "1",
  "descripcion": null,
  "mensaje": null,
  "error": null,
  "rnc": "40211932609",
  "encf": "E410000000001",
  "secuenciaUtilizada": true,
  "fechaRecepcion": "5/28/2026 12:40:43 AM",
  "mensajes": [
    {
      "valor": "",
      "codigo": 0
    }
  ],
  "httpStatus": 200,
  "raw": "{\"trackId\":\"9f971e0f-9e3b-46cd-a767-2478893eaa9b\",\"codigo\":\"1\",\"estado\":\"Aceptado\",\"rnc\":\"40211932609\",\"encf\":\"E410000000001\",\"secuenciaUtilizada\":true,\"fechaRecepcion\":\"5/28/2026 12:40:43 AM\",\"mensajes\":[{\"valor\":\"\",\"codigo\":0}]}",
  "statusPath": "storage/ecf/tracks/estado-9f971e0f-9e3b-46cd-a767-2478893eaa9b.json"
}
