{
  "trackId": "8d2ac6f2-9d3a-44cd-a435-1fb66cf96863",
  "fecha": "2026-05-25T22:20:00.546Z",
  "estado": "ACEPTADO",
  "environment": "certecf",
  "codigo": "1",
  "descripcion": null,
  "mensaje": null,
  "error": null,
  "rnc": "40211932609",
  "encf": "E460000000011",
  "secuenciaUtilizada": true,
  "fechaRecepcion": "5/25/2026 6:19:20 PM",
  "mensajes": [
    {
      "valor": "",
      "codigo": 0
    }
  ],
  "httpStatus": 200,
  "raw": "{\"trackId\":\"8d2ac6f2-9d3a-44cd-a435-1fb66cf96863\",\"codigo\":\"1\",\"estado\":\"Aceptado\",\"rnc\":\"40211932609\",\"encf\":\"E460000000011\",\"secuenciaUtilizada\":true,\"fechaRecepcion\":\"5/25/2026 6:19:20 PM\",\"mensajes\":[{\"valor\":\"\",\"codigo\":0}]}",
  "statusPath": "storage/ecf/tracks/estado-8d2ac6f2-9d3a-44cd-a435-1fb66cf96863.json"
}
