{
  "trackId": "d400f6eb-7a67-47e1-8449-fa6c4295fd4e",
  "fecha": "2026-05-27T13:56:38.297Z",
  "estado": "RECHAZADO",
  "environment": "certecf",
  "codigo": "2",
  "descripcion": null,
  "mensaje": null,
  "error": null,
  "rnc": "40211932609",
  "encf": "E310000000003",
  "secuenciaUtilizada": false,
  "fechaRecepcion": "5/27/2026 9:55:22 AM",
  "mensajes": [
    {
      "valor": "La propiedad NombreComercial no es válida debido a que el valor enviado () no coincide con el valor (DOCUMENTOS ELECTRONICOS DE 02) del conjunto de datos entregados.",
      "codigo": 0
    }
  ],
  "httpStatus": 200,
  "raw": "{\"trackId\":\"d400f6eb-7a67-47e1-8449-fa6c4295fd4e\",\"codigo\":\"2\",\"estado\":\"Rechazado\",\"rnc\":\"40211932609\",\"encf\":\"E310000000003\",\"secuenciaUtilizada\":false,\"fechaRecepcion\":\"5/27/2026 9:55:22 AM\",\"mensajes\":[{\"valor\":\"La propiedad NombreComercial no es válida debido a que el valor enviado () no coincide con el valor (DOCUMENTOS ELECTRONICOS DE 02) del conjunto de datos entregados.\",\"codigo\":0}]}",
  "statusPath": "storage/ecf/tracks/estado-d400f6eb-7a67-47e1-8449-fa6c4295fd4e.json"
}
