{
  "trackId": "e34a6a81-0949-4f1a-87db-1a8f0be8a2a2",
  "fecha": "2026-05-26T01:28:03.916Z",
  "estado": "ACEPTADO",
  "environment": "certecf",
  "codigo": "1",
  "descripcion": null,
  "mensaje": null,
  "error": null,
  "rnc": "40211932609",
  "encf": "E450000000008",
  "secuenciaUtilizada": true,
  "fechaRecepcion": "5/25/2026 9:27:22 PM",
  "mensajes": [
    {
      "valor": "",
      "codigo": 0
    }
  ],
  "httpStatus": 200,
  "raw": "{\"trackId\":\"e34a6a81-0949-4f1a-87db-1a8f0be8a2a2\",\"codigo\":\"1\",\"estado\":\"Aceptado\",\"rnc\":\"40211932609\",\"encf\":\"E450000000008\",\"secuenciaUtilizada\":true,\"fechaRecepcion\":\"5/25/2026 9:27:22 PM\",\"mensajes\":[{\"valor\":\"\",\"codigo\":0}]}",
  "statusPath": "storage/ecf/tracks/estado-e34a6a81-0949-4f1a-87db-1a8f0be8a2a2.json"
}
