{
  "trackId": "598d6775-7534-441a-bb69-54d45c0b889a",
  "fecha": "2026-05-27T12:39:30.241Z",
  "estado": "ACEPTADO",
  "environment": "certecf",
  "codigo": "1",
  "descripcion": null,
  "mensaje": null,
  "error": null,
  "rnc": "40211932609",
  "encf": "E320000000001",
  "secuenciaUtilizada": true,
  "fechaRecepcion": "5/27/2026 8:38:12 AM",
  "mensajes": [
    {
      "valor": "",
      "codigo": 0
    }
  ],
  "httpStatus": 200,
  "raw": "{\"trackId\":\"598d6775-7534-441a-bb69-54d45c0b889a\",\"codigo\":\"1\",\"estado\":\"Aceptado\",\"rnc\":\"40211932609\",\"encf\":\"E320000000001\",\"secuenciaUtilizada\":true,\"fechaRecepcion\":\"5/27/2026 8:38:12 AM\",\"mensajes\":[{\"valor\":\"\",\"codigo\":0}]}",
  "statusPath": "storage/ecf/tracks/estado-598d6775-7534-441a-bb69-54d45c0b889a.json"
}
