{
  "trackId": "f688e773-fe73-4991-a7b4-fa46463b47ff",
  "fecha": "2026-05-25T11:27:55.476Z",
  "estado": "RECHAZADO",
  "environment": "certecf",
  "codigo": "2",
  "descripcion": null,
  "mensaje": null,
  "error": null,
  "rnc": "40211932609",
  "encf": "E430000000010",
  "secuenciaUtilizada": false,
  "fechaRecepcion": "5/25/2026 7:27:56 AM",
  "mensajes": [
    {
      "valor": "El formato del XML no es válido.",
      "codigo": 1
    }
  ],
  "httpStatus": 200,
  "raw": "{\"trackId\":\"f688e773-fe73-4991-a7b4-fa46463b47ff\",\"codigo\":\"2\",\"estado\":\"Rechazado\",\"rnc\":\"40211932609\",\"encf\":\"E430000000010\",\"secuenciaUtilizada\":false,\"fechaRecepcion\":\"5/25/2026 7:27:56 AM\",\"mensajes\":[{\"valor\":\"El formato del XML no es válido.\",\"codigo\":1}]}",
  "statusPath": "storage/ecf/tracks/estado-f688e773-fe73-4991-a7b4-fa46463b47ff.json"
}
