{
  "trackId": "11ef848f-5665-45ec-8516-02d0707bef5f",
  "fecha": "2026-05-27T00:33:58.591Z",
  "estado": "PROCESANDO",
  "environment": "certecf",
  "codigo": "3",
  "descripcion": null,
  "mensaje": null,
  "error": null,
  "rnc": "40211932609",
  "encf": "E330000000001",
  "secuenciaUtilizada": false,
  "fechaRecepcion": "5/26/2026 8:33:58 PM",
  "mensajes": [
    {
      "valor": "",
      "codigo": 0
    }
  ],
  "httpStatus": 200,
  "raw": "{\"trackId\":\"11ef848f-5665-45ec-8516-02d0707bef5f\",\"codigo\":\"3\",\"estado\":\"En Proceso\",\"rnc\":\"40211932609\",\"encf\":\"E330000000001\",\"secuenciaUtilizada\":false,\"fechaRecepcion\":\"5/26/2026 8:33:58 PM\",\"mensajes\":[{\"valor\":\"\",\"codigo\":0}]}",
  "statusPath": "storage/ecf/tracks/estado-11ef848f-5665-45ec-8516-02d0707bef5f.json"
}
