{
  "trackId": "c5f1bbb4-f1f4-4fa9-994b-cb967d793239",
  "fecha": "2026-05-26T05:16:37.860Z",
  "estado": "ACEPTADO",
  "environment": "certecf",
  "codigo": "1",
  "descripcion": null,
  "mensaje": null,
  "error": null,
  "rnc": "40211932609",
  "encf": "E320000000001",
  "secuenciaUtilizada": true,
  "fechaRecepcion": "5/26/2026 1:15:27 AM",
  "mensajes": [
    {
      "valor": "",
      "codigo": 0
    }
  ],
  "httpStatus": 200,
  "raw": "{\"trackId\":\"c5f1bbb4-f1f4-4fa9-994b-cb967d793239\",\"codigo\":\"1\",\"estado\":\"Aceptado\",\"rnc\":\"40211932609\",\"encf\":\"E320000000001\",\"secuenciaUtilizada\":true,\"fechaRecepcion\":\"5/26/2026 1:15:27 AM\",\"mensajes\":[{\"valor\":\"\",\"codigo\":0}]}",
  "statusPath": "storage/ecf/tracks/estado-c5f1bbb4-f1f4-4fa9-994b-cb967d793239.json"
}
